cryptoapi/__init__.py
cryptoapi/bitfinex.py
cryptoapi/bitvavo.py
cryptoapi/coinbasepro.py
cryptoapi/kraken.py
cryptoapi/base/__init__.py
cryptoapi/base/errors.py
cryptoapi/base/exchange.py
cryptoapi-0.1.22.dist-info/LICENSE
cryptoapi-0.1.22.dist-info/METADATA
cryptoapi-0.1.22.dist-info/WHEEL
cryptoapi-0.1.22.dist-info/top_level.txt
cryptoapi-0.1.22.dist-info/RECORD
