Metadata-Version: 2.1
Name: cryptoapi
Version: 0.1.22
Summary: Asynchronous cryptocurrency REST and websocket API with support for multiple exchanges.
Home-page: https://github.com/joshklop/cryptoapi
Author: Josh Klopfenstein
Author-email: joshklop@gmail.com
License: MIT
Keywords: websocket rest api cryptocurrency exchange coinbasepro kraken bitvavo bitfinex
Platform: UNKNOWN
Classifier: License :: OSI Approved :: MIT License
Classifier: Programming Language :: Python :: 3
Classifier: Programming Language :: Python :: 3.8
Requires-Dist: aiolimiter
Requires-Dist: ccxt
Requires-Dist: websockets
